km3compass/__init__.py
km3compass/acceptance_tests.py
km3compass/calibration.py
km3compass/calibration_object.py
km3compass/definitions.py
km3compass/readerCSK.py
km3compass/readerOnline.py
km3compass/tools.py
km3compass/toolsDB.py
km3compass/version.py
km3compass/cli/acceptance_tests.py
km3compass/cli/display_csk.py
km3compass/cli/generate_calibration.py
km3compass/cli/print_calibration.py
km3compass-0.7.1.dist-info/LICENSE
km3compass-0.7.1.dist-info/METADATA
km3compass-0.7.1.dist-info/WHEEL
km3compass-0.7.1.dist-info/entry_points.txt
km3compass-0.7.1.dist-info/top_level.txt
km3compass-0.7.1.dist-info/RECORD
