Metadata-Version: 2.1
Name: km3compass
Version: 0.7.1
Summary: Light weight package to read and exploit km3net compass data
Home-page: https://git.km3net.de/km3py/km3compass
Author: Valentin Pestel
Author-email: vpestel@km3net.de
License: UNKNOWN
Platform: any
Classifier: Intended Audience :: Developers
Classifier: Intended Audience :: Science/Research
Classifier: Programming Language :: Python
Requires-Python: >=3.8
Requires-Dist: setuptools-scm
Requires-Dist: pandas
Requires-Dist: numpy
Requires-Dist: km3db>=v0.12.0
Requires-Dist: scipy
Requires-Dist: scikit-learn
Requires-Dist: matplotlib
Requires-Dist: tables
Provides-Extra: dev
Requires-Dist: black; extra == "dev"
Requires-Dist: matplotlib; extra == "dev"
Requires-Dist: numpydoc; extra == "dev"
Requires-Dist: pillow; extra == "dev"
Requires-Dist: pytest; extra == "dev"
Requires-Dist: pytest-cov; extra == "dev"
Requires-Dist: pytest-flake8; extra == "dev"
Requires-Dist: pytest-pylint; extra == "dev"
Requires-Dist: pytest-watch; extra == "dev"
Requires-Dist: sphinx; extra == "dev"
Requires-Dist: sphinx-autoapi; extra == "dev"
Requires-Dist: sphinx-gallery>=0.1.12; extra == "dev"
Requires-Dist: sphinx-rtd-theme; extra == "dev"
Requires-Dist: sphinxcontrib-versioning; extra == "dev"
Requires-Dist: wheel; extra == "dev"
